litepolis_database_default/Actor.py
litepolis_database_default/Comments.py
litepolis_database_default/Conversations.py
litepolis_database_default/MigrationRecord.py
litepolis_database_default/Users.py
litepolis_database_default/Vote.py
litepolis_database_default/__init__.py
litepolis_database_default/utils.py
litepolis_database_default/utils_StarRocks.py
litepolis_database_default-0.0.4.dist-info/licenses/LICENSE
litepolis_database_default-0.0.4.dist-info/METADATA
litepolis_database_default-0.0.4.dist-info/WHEEL
litepolis_database_default-0.0.4.dist-info/top_level.txt
litepolis_database_default-0.0.4.dist-info/RECORD
