Metadata-Version: 2.4
Name: litepolis-database-default
Version: 0.0.4
Summary: The default database module for LitePolis that compatible with Polis
Author: NewJerseyStyle
License: file: LICENSE
Project-URL: Homepage, https://github.com/NewJerseyStyle/LitePolis-database-default
License-File: LICENSE
Requires-Dist: fastapi
Requires-Dist: sqlmodel
Requires-Dist: sqlparse
Requires-Dist: inflection
Requires-Dist: starrocks
Dynamic: license-file
